{
    "logo": {
        "url": "/images/logo-dark.svg",
        "altText": "General Phở Vietnamese Kitchen",
        "styles": {
            "self": {
                "margin": [
                    "mr-3"
                ]
            }
        },
        "type": "ImageBlock"
    },
    "primaryLinks": [
        {
            "label": "Menu",
            "altText": "View our menu",
            "url": "/menu",
            "icon": "arrowRight",
            "iconPosition": "right",
            "style": "secondary",
            "type": "Link"
        },
        {
            "label": "About",
            "altText": "About us",
            "url": "/about",
            "icon": "arrowRight",
            "iconPosition": "right",
            "style": "secondary",
            "type": "Link"
        },
        {
            "label": "Contact",
            "altText": "Contact us",
            "url": "/contact",
            "icon": "arrowRight",
            "iconPosition": "right",
            "style": "secondary",
            "type": "Link"
        }
    ],
    "secondaryLinks": [
        {
            "label": "Visit Us",
            "altText": "Visit our location",
            "url": "/contact",
            "icon": "arrowRight",
            "iconPosition": "right",
            "style": "primary",
            "type": "Button"
        }
    ],
    "variant": "logo-left-primary-nav-centered",
    "colors": "bg-light-fg-dark",
    "type": "Header"
}